djadyen/__init__.py
djadyen/admin.py
djadyen/choices.py
djadyen/conf.py
djadyen/constants.py
djadyen/models.py
djadyen/settings.py
djadyen/utils.py
djadyen/views.py
djadyen/management/__init__.py
djadyen/management/commands/__init__.py
djadyen/management/commands/adyen_maintenance.py
djadyen/management/commands/sync_payment_methods.py
djadyen/migrations/0001_initial.py
djadyen/migrations/__init__.py
djadyen/notifications/__init__.py
djadyen/notifications/signing.py
djadyen/notifications/urls.py
djadyen/notifications/views.py
djadyen/static/djadyen/djadyen.css
djadyen/static/djadyen/djadyen.js
djadyen/templates/adyen/component.html
djadyen/templates/adyen/pay.html
djadyen/templates/adyen/polling.html
djadyen/templatetags/__init__.py
djadyen/templatetags/adyen_tags.py
djadyen-4.0.0.dist-info/METADATA
djadyen-4.0.0.dist-info/WHEEL
djadyen-4.0.0.dist-info/top_level.txt
djadyen-4.0.0.dist-info/RECORD
